dicter/__init__.py
dicter/dicter.py
dicter/examples.py
dicter-0.1.7.dist-info/licenses/LICENSE
dicter-0.1.7.dist-info/METADATA
dicter-0.1.7.dist-info/WHEEL
dicter-0.1.7.dist-info/top_level.txt
dicter-0.1.7.dist-info/RECORD
