Metadata-Version: 2.4
Name: dicter
Version: 0.1.7
Summary: dicter is a Python package with advanced dictionary functions.
Author-email: Erdogan Taskesen <erdogant@gmail.com>
License: MIT License
Project-URL: Homepage, https://erdogant.github.io/dicter
Project-URL: Download, https://github.com/erdogant/dicter/archive/{version}.tar.gz
Keywords: Python,
Classifier: Programming Language :: Python :: 3
Classifier: License :: OSI Approved :: MIT License
Classifier: Operating System :: OS Independent
Requires-Python: >=3
License-File: LICENSE
Requires-Dist: pandas
Requires-Dist: numpy
Requires-Dist: tqdm
Dynamic: license-file
